idiary/__init__.py
idiary/main.py
idiary/version.py
idiary/utils/__init__.py
idiary/utils/common.py
idiary-0.0.1.dist-info/METADATA
idiary-0.0.1.dist-info/WHEEL
idiary-0.0.1.dist-info/entry_points.txt
idiary-0.0.1.dist-info/top_level.txt
idiary-0.0.1.dist-info/RECORD
