Metadata-Version: 2.1
Name: idiary
Version: 0.0.1
Summary: Personal Diary Software
Home-page: https://github.com/zhaojb17/idiary
Author: Junbo Zhao
Author-email: zhaojb17@mails.tsinghua.edu.cn
License: MIT
Platform: UNKNOWN
Classifier: Programming Language :: Python :: 3
Classifier: Operating System :: OS Independent
Classifier: License :: OSI Approved :: MIT License
Requires-Dist: click
Requires-Dist: pyyaml
Requires-Dist: setproctitle
